hesitate/__init__.py
hesitate/conf.py
hesitate/driver.py
hesitate/rewriter.py
hesitate/wrappers/__init__.py
hesitate/wrappers/django/__init__.py
hesitate-0.0.2.dist-info/DESCRIPTION.rst
hesitate-0.0.2.dist-info/METADATA
hesitate-0.0.2.dist-info/metadata.json
hesitate-0.0.2.dist-info/RECORD
hesitate-0.0.2.dist-info/top_level.txt
hesitate-0.0.2.dist-info/WHEEL
