Metadata-Version: 2.0
Name: hesitate
Version: 0.0.2
Summary: A stochastic Design by Contract utility
Home-page: https://github.com/mhallin/hesitate-py
Author: Magnus Hallin
Author-email: mhallin@gmail.com
License: BSD
Platform: UNKNOWN
